xpipe_cli/__init__.py
xpipe_cli/cli.py
xpipe_cli-0.1.14.dist-info/entry_points.txt
xpipe_cli-0.1.14.dist-info/LICENSE
xpipe_cli-0.1.14.dist-info/METADATA
xpipe_cli-0.1.14.dist-info/WHEEL
xpipe_cli-0.1.14.dist-info/RECORD
