Metadata-Version: 2.1
Name: xpipe-cli
Version: 0.1.14
Summary: CLI that talks to the XPipe HTTP API
Home-page: https://github.com/coandco/xpipe_cli
Author: Clint Olson
Author-email: coandco@gmail.com
Requires-Python: >=3.10,<4.0
Classifier: Programming Language :: Python :: 3
Classifier: Programming Language :: Python :: 3.10
Classifier: Programming Language :: Python :: 3.11
Classifier: Programming Language :: Python :: 3.12
Requires-Dist: click (>=8.1.7,<9.0.0)
Requires-Dist: prettytable (>=3.10.0,<4.0.0)
Requires-Dist: requests-toolbelt (>=1.0.0,<2.0.0)
Requires-Dist: tqdm (>=4.66.4,<5.0.0)
Requires-Dist: xpipe-client (>=0.1.26,<0.2.0)
Project-URL: Repository, https://github.com/coandco/xpipe_cli
